g3w_config_scripts/__init__.py
g3w_config_scripts/g3w_config.py
g3w_config_scripts/g3w_dev_setup.py
g3w_config_scripts/g3w_prod_setup.py
g3w_config_scripts-0.1.0.dist-info/METADATA
g3w_config_scripts-0.1.0.dist-info/WHEEL
g3w_config_scripts-0.1.0.dist-info/entry_points.txt
g3w_config_scripts-0.1.0.dist-info/top_level.txt
g3w_config_scripts-0.1.0.dist-info/RECORD
