Metadata-Version: 2.1
Name: g3w_config_scripts
Version: 0.1.0
Home-page: https://github.com/moovida/g3w_config_scripts
Author: Andrea Antonello
Author-email: andrea.antonello@gmail.com
Classifier: Programming Language :: Python :: 3
Classifier: License :: OSI Approved :: MIT License
Classifier: Operating System :: OS Independent
Requires-Python: >=3.7
